indexed_class.py
setup.py
tests/__init__.py
tests/integration/__init__.py
tests/unit/__init__.py
tests/unit/test_imports.py
tests/unit/test_indexed_class.py
indexed_class-1.0.1.dist-info/LICENSE.md
indexed_class-1.0.1.dist-info/METADATA
indexed_class-1.0.1.dist-info/WHEEL
indexed_class-1.0.1.dist-info/top_level.txt
indexed_class-1.0.1.dist-info/RECORD
