Metadata-Version: 2.1
Name: indexed-class
Version: 1.0.1
Summary: A mechanism for subclass tree indexation.
Home-page: https://gitlab.com/pyutil/indexed_class
Author: aachn3
Author-email: n45t31@protonmail.com
Classifier: Programming Language :: Python :: 3
Classifier: Operating System :: OS Independent
Requires-Python: >=3.6.0
License-File: LICENSE.md
